skylight/__init__.py
skylight/_static.py
skylight/ephemeris.py
skylight/exceptions.py
skylight/geometry.py
skylight/observer.py
skylight/render.py
skylight/sky.py
skylight/prague/__init__.py
skylight/prague/io.py
skylight/prague/prague.py
skylight-1.1.dist-info/LICENSE
skylight-1.1.dist-info/METADATA
skylight-1.1.dist-info/WHEEL
skylight-1.1.dist-info/top_level.txt
skylight-1.1.dist-info/RECORD
