Metadata-Version: 2.1
Name: skylight
Version: 1.1
Summary: A package providing radiance, polarisation, and transmittance information from the daylight.
Home-page: https://pypi.org/project/skylight/
Author: Evripidis Gkanias
Author-email: ev.gkanias@ed.ac.uk
Maintainer: Evripidis Gkanias
Maintainer-email: ev.gkanias@ed.ac.uk
License: GPLv3+
Project-URL: Bug Tracker, https://github.com/evgkanias/sky/issues
Project-URL: Source, https://github.com/evgkanias/sky
Classifier: Programming Language :: Python :: 3.9
Classifier: Intended Audience :: Science/Research
Classifier: Topic :: Scientific/Engineering :: Atmospheric Science
Classifier: License :: OSI Approved :: GNU General Public License v3 or later (GPLv3+)
Classifier: Operating System :: OS Independent
Classifier: Operating System :: Microsoft :: Windows :: Windows 11
Classifier: Topic :: Scientific/Engineering :: Atmospheric Science
Classifier: Topic :: Scientific/Engineering :: Physics
Requires-Python: >=3.9
License-File: LICENSE
Requires-Dist: numpy>=1.23.4
Requires-Dist: scipy>=1.9.3
Requires-Dist: numba>=0.56.3
Requires-Dist: pytz~=2021.1
Requires-Dist: pyyaml>=6.0
Requires-Dist: requests>=2.9.2
